temod/__init__.py
temod/base/__init__.py
temod/base/attribute.py
temod/base/cluster.py
temod/base/condition.py
temod/base/constraint.py
temod/base/entity.py
temod/base/exceptions.py
temod/base/join.py
temod/ext/holders.py
temod/operators/aggregation.py
temod/storage/__init__.py
temod/storage/exceptions.py
temod/storage/directory/__init__.py
temod/storage/directory/directoryStorage.py
temod/storage/directory/yamlStorage.py
temod/storage/influxdb/influxEntityStorage.py
temod/storage/influxdb/influxStorage.py
temod/storage/influxdb/influxTranslators.py
temod/storage/mysql/__init__.py
temod/storage/mysql/mysqlAttributesTranslator.py
temod/storage/mysql/mysqlClusterStorage.py
temod/storage/mysql/mysqlConditionsTranslator.py
temod/storage/mysql/mysqlEntityStorage.py
temod/storage/mysql/mysqlJoinStorage.py
temod/storage/mysql/mysqlStorage.py
temod/utils/decorators.py
temod/utils/exoskeleton.py
temod/utils/graphs.py
temod/utils/installer/common.py
temod/utils/installer/storage/mysql/mysql_setup.py
temod/utils/synchronizer/__init__.py
temod/utils/synchronizer/simple.py
temod/utils/synchronizer/unidirectional.py
temod-2.2.3.dist-info/licenses/LICENSE.txt
temod-2.2.3.dist-info/METADATA
temod-2.2.3.dist-info/WHEEL
temod-2.2.3.dist-info/top_level.txt
temod-2.2.3.dist-info/RECORD
