Metadata-Version: 2.4
Name: temod
Version: 2.2.3
Summary: Data management abstraction layer for your python programs
Author-email: PyAxolotl <abdellatifzied.saada@gmail.com>
Project-URL: Homepage, https://github.com/TuburboMajus/temod
Project-URL: Bug Tracker, https://github.com/TuburboMajus/temod/issues
Classifier: Programming Language :: Python :: 3
Classifier: License :: OSI Approved :: MIT License
Classifier: Operating System :: OS Independent
Requires-Python: >=3.7
License-File: LICENSE.txt
Requires-Dist: networkx>=3.1
Requires-Dist: mysql-connector-python>=8.3.0
Requires-Dist: PyYaml>=6.0
Requires-Dist: bcrypt>=4.1.3
Dynamic: license-file
